{"name":"Search for an automation course","id":"choucair-academy;search-for-an-automation-course","testSteps":[{"number":1,"description":"Given than user wants to learn automation in the Choucair Academy","duration":38366,"startTime":"2021-06-23T10:14:45.393-05:00[America/Bogota]","screenshots":[{"screenshot":"489cbfc56de5b0f12b855fb6dc1aa8356e6d92cb3bd790682b740852b0a0eb71.png"}],"result":"SUCCESS","precondition":false,"children":[{"number":2,"description":"User opens the Choucair academy page","duration":14384,"startTime":"2021-06-23T10:14:45.848-05:00[America/Bogota]","screenshots":[{"screenshot":"284a3a899e17400a98f5f77be85bbd839b8a070e05cf2cb03b9946aca6424ca1.png"}],"result":"SUCCESS","precondition":false},{"number":3,"description":"User clicks on PulsaElBotonParaIngresar","duration":845,"startTime":"2021-06-23T10:15:00.293-05:00[America/Bogota]","screenshots":[{"screenshot":"a7d976d092dca81432a88745f65cf3d32c520a251641e15c44ed5dd96bce2890.png"}],"result":"SUCCESS","precondition":false},{"number":4,"description":"User enters \u0027bbozonb\u0027 into IngresaTuUsuario","duration":709,"startTime":"2021-06-23T10:15:01.140-05:00[America/Bogota]","screenshots":[{"screenshot":"3d574a3ee0f561534414d70188c57bb470ce4b6b63bad5594307edae92313fa3.png"}],"result":"SUCCESS","precondition":false},{"number":5,"description":"User enters \u0027Choucair2021*\u0027 into IngresaTuContrase침a*","duration":913,"startTime":"2021-06-23T10:15:01.851-05:00[America/Bogota]","screenshots":[{"screenshot":"5dca5467602598fd6fe127305657ecb37511af5a402b49f7371e1bfddd289430.png"}],"result":"SUCCESS","precondition":false},{"number":6,"description":"User clicks on presionaParaAcceder","duration":20728,"startTime":"2021-06-23T10:15:02.767-05:00[America/Bogota]","screenshots":[{"screenshot":"489cbfc56de5b0f12b855fb6dc1aa8356e6d92cb3bd790682b740852b0a0eb71.png"}],"result":"SUCCESS","precondition":false}]},{"number":7,"description":"When user search for the course Automatizaci칩n de Pruebas in the Choucair Academy platform","duration":10654,"startTime":"2021-06-23T10:15:23.760-05:00[America/Bogota]","screenshots":[{"screenshot":"14914658249564b170f49e75c2a5538054c66393c38a05668d44c1f29a963ce6.png"}],"result":"SUCCESS","precondition":false,"children":[{"number":8,"description":"User clicks on Seleciona la universidad choucair","duration":1606,"startTime":"2021-06-23T10:15:23.807-05:00[America/Bogota]","screenshots":[{"screenshot":"bb7d21f2dd41644855f8f0b6775c6dfd0dbf4489e70e9a0227b2f1b5fc0cdb2b.png"}],"result":"SUCCESS","precondition":false},{"number":9,"description":"User enters \u0027Automatizaci칩n de Pruebas\u0027 into Buscar el curso","duration":427,"startTime":"2021-06-23T10:15:25.415-05:00[America/Bogota]","screenshots":[{"screenshot":"ec5a1cd4be40ef7522ebeb717dfb7da8d8d63cb1d3c493746f88584606d56c8e.png"}],"result":"SUCCESS","precondition":false},{"number":10,"description":"User clicks on Da clic para buscar el curso","duration":2082,"startTime":"2021-06-23T10:15:25.843-05:00[America/Bogota]","screenshots":[{"screenshot":"509dbd72e847f921384dfa009ef593883c77010bce4780e1d0782d521da7b38a.png"}],"result":"SUCCESS","precondition":false},{"number":11,"description":"User clicks on Da clic para buscar el curso","duration":6126,"startTime":"2021-06-23T10:15:27.927-05:00[America/Bogota]","screenshots":[{"screenshot":"14914658249564b170f49e75c2a5538054c66393c38a05668d44c1f29a963ce6.png"}],"result":"SUCCESS","precondition":false}]},{"number":12,"description":"Then user finds the course called Automatizaci칩n de Pruebas","duration":1142,"startTime":"2021-06-23T10:15:34.415-05:00[America/Bogota]","screenshots":[{"screenshot":"14914658249564b170f49e75c2a5538054c66393c38a05668d44c1f29a963ce6.png"}],"result":"SUCCESS","precondition":false,"children":[{"number":13,"description":"Then answer","duration":596,"startTime":"2021-06-23T10:15:34.550-05:00[America/Bogota]","screenshots":[{"screenshot":"14914658249564b170f49e75c2a5538054c66393c38a05668d44c1f29a963ce6.png"}],"result":"SUCCESS","precondition":false}]}],"userStory":{"id":"choucair-academy","storyName":"Choucair Academy","path":"src/test/resources/features/academyChoucair.feature","narrative":"  As a user, I want to learn how to automate in screenplay at the Choucair Academy with the automation course","type":"feature"},"featureTag":{"name":"Features/Choucair Academy","type":"feature"},"title":"Search for an automation course","tags":[{"name":"scenario","type":"tag"},{"name":"Choucair academy","type":"feature"},{"name":"stories","type":"tag"}],"startTime":"2021-06-23T10:14:44.822-05:00[America/Bogota]","duration":50989,"projectKey":"","sessionId":"ee9ebabe2850989041938ece74123d79","driver":"chrome:user","manual":false,"testSource":"Cucumber","result":"SUCCESS"}